[
  {
    "company": "Mertz, Ullrich and Jerde",
    "position": "Senior Sales Associate",
    "status": "declined",
    "jobType": "full-time",
    "createdBy": "641924257fc4b31d10ec23d4",
    "createdAt": "2022-01-22T11:41:42Z"
  },
  {
    "company": "DuBuque LLC",
    "position": "Account Representative IV",
    "status": "pending",
    "jobType": "internship",
    "createdBy": "641924257fc4b31d10ec23d4",
    "createdAt": "2023-02-07T11:07:06Z"
  },
  {
    "company": "Mann, Okuneva and Bauch",
    "position": "Assistant Manager",
    "status": "interview",
    "jobType": "internship",
    "createdBy": "641924257fc4b31d10ec23d4",
    "createdAt": "2022-03-24T03:08:58Z"
  },
  {
    "company": "Mann LLC",
    "position": "VP Product Management",
    "status": "pending",
    "jobType": "part-time",
    "createdBy": "641924257fc4b31d10ec23d4",
    "createdAt": "2023-03-15T20:29:05Z"
  },
  {
    "company": "Hayes Inc",
    "position": "Office Assistant I",
    "status": "pending",
    "jobType": "part-time",
    "createdBy": "641924257fc4b31d10ec23d4",
    "createdAt": "2023-03-19T12:08:21Z"
  },
  {
    "company": "Goyette, Tillman and Beahan",
    "position": "Tax Accountant",
    "status": "declined",
    "jobType": "part-time",
    "createdBy": "641924257fc4b31d10ec23d4",
    "createdAt": "2022-01-11T10:38:35Z"
  },
  {
    "company": "Murray-Hegmann",
    "position": "Help Desk Technician",
    "status": "declined",
    "jobType": "remote",
    "createdBy": "641924257fc4b31d10ec23d4",
    "createdAt": "2022-01-30T20:55:06Z"
  },
  {
    "company": "Hand, Heathcote and Senger",
    "position": "Desktop Support Technician",
    "status": "pending",
    "jobType": "remote",
    "createdBy": "641924257fc4b31d10ec23d4",
    "createdAt": "2021-08-12T22:02:41Z"
  },
  {
    "company": "Von-Dickinson",
    "position": "Clinical Specialist",
    "status": "interview",
    "jobType": "part-time",
    "createdBy": "641924257fc4b31d10ec23d4",
    "createdAt": "2021-09-14T02:33:44Z"
  },
  {
    "company": "Reichel, Goldner and Jakubowski",
    "position": "Cost Accountant",
    "status": "declined",
    "jobType": "full-time",
    "createdBy": "641924257fc4b31d10ec23d4",
    "createdAt": "2021-12-28T03:24:06Z"
  },
  {
    "company": "Weimann-Fritsch",
    "position": "Account Representative I",
    "status": "declined",
    "jobType": "internship",
    "createdBy": "641924257fc4b31d10ec23d4",
    "createdAt": "2022-06-26T21:08:42Z"
  },
  {
    "company": "Purdy, Jast and Welch",
    "position": "Occupational Therapist",
    "status": "interview",
    "jobType": "internship",
    "createdBy": "641924257fc4b31d10ec23d4",
    "createdAt": "2022-02-17T22:40:59Z"
  },
  {
    "company": "Stanton and Sons",
    "position": "Food Chemist",
    "status": "interview",
    "jobType": "part-time",
    "createdBy": "641924257fc4b31d10ec23d4",
    "createdAt": "2021-12-14T20:36:26Z"
  },
  {
    "company": "Gutkowski-Dach",
    "position": "Statistician IV",
    "status": "declined",
    "jobType": "part-time",
    "createdBy": "641924257fc4b31d10ec23d4",
    "createdAt": "2022-04-03T15:21:45Z"
  },
  {
    "company": "Mann Inc",
    "position": "Speech Pathologist",
    "status": "interview",
    "jobType": "remote",
    "createdBy": "641924257fc4b31d10ec23d4",
    "createdAt": "2021-10-26T12:08:53Z"
  },
  {
    "company": "Jakubowski, Rosenbaum and Lockman",
    "position": "Software Consultant",
    "status": "interview",
    "jobType": "part-time",
    "createdBy": "641924257fc4b31d10ec23d4",
    "createdAt": "2021-09-26T13:06:23Z"
  },
  {
    "company": "O'Hara-Braun",
    "position": "Accountant III",
    "status": "pending",
    "jobType": "full-time",
    "createdBy": "641924257fc4b31d10ec23d4",
    "createdAt": "2022-12-04T09:55:58Z"
  },
  {
    "company": "King-Legros",
    "position": "VP Quality Control",
    "status": "interview",
    "jobType": "full-time",
    "createdBy": "641924257fc4b31d10ec23d4",
    "createdAt": "2022-05-30T17:21:31Z"
  },
  {
    "company": "Friesen LLC",
    "position": "Community Outreach Specialist",
    "status": "interview",
    "jobType": "remote",
    "createdBy": "641924257fc4b31d10ec23d4",
    "createdAt": "2021-07-03T19:31:20Z"
  },
  {
    "company": "Breitenberg, Gottlieb and Borer",
    "position": "Speech Pathologist",
    "status": "pending",
    "jobType": "internship",
    "createdBy": "641924257fc4b31d10ec23d4",
    "createdAt": "2021-10-02T15:35:28Z"
  },
  {
    "company": "White, Schmitt and O'Connell",
    "position": "Senior Developer",
    "status": "declined",
    "jobType": "full-time",
    "createdBy": "641924257fc4b31d10ec23d4",
    "createdAt": "2022-05-08T19:30:12Z"
  },
  {
    "company": "Streich, Zieme and Padberg",
    "position": "Speech Pathologist",
    "status": "interview",
    "jobType": "part-time",
    "createdBy": "641924257fc4b31d10ec23d4",
    "createdAt": "2021-11-14T02:46:19Z"
  },
  {
    "company": "Fadel-Miller",
    "position": "Software Test Engineer I",
    "status": "interview",
    "jobType": "part-time",
    "createdBy": "641924257fc4b31d10ec23d4",
    "createdAt": "2023-04-12T04:48:42Z"
  },
  {
    "company": "Crist LLC",
    "position": "Structural Engineer",
    "status": "interview",
    "jobType": "internship",
    "createdBy": "641924257fc4b31d10ec23d4",
    "createdAt": "2021-04-26T10:56:11Z"
  },
  {
    "company": "O'Kon and Sons",
    "position": "Staff Accountant IV",
    "status": "interview",
    "jobType": "part-time",
    "createdBy": "641924257fc4b31d10ec23d4",
    "createdAt": "2023-03-16T22:56:54Z"
  },
  {
    "company": "Swaniawski-Streich",
    "position": "Programmer IV",
    "status": "interview",
    "jobType": "remote",
    "createdBy": "641924257fc4b31d10ec23d4",
    "createdAt": "2023-03-24T20:02:20Z"
  },
  {
    "company": "Wilkinson, Rodriguez and Glover",
    "position": "Analog Circuit Design manager",
    "status": "declined",
    "jobType": "remote",
    "createdBy": "641924257fc4b31d10ec23d4",
    "createdAt": "2021-08-17T09:43:09Z"
  },
  {
    "company": "Anderson-Bechtelar",
    "position": "Social Worker",
    "status": "declined",
    "jobType": "part-time",
    "createdBy": "641924257fc4b31d10ec23d4",
    "createdAt": "2022-01-29T16:53:15Z"
  },
  {
    "company": "Dicki LLC",
    "position": "VP Accounting",
    "status": "interview",
    "jobType": "part-time",
    "createdBy": "641924257fc4b31d10ec23d4",
    "createdAt": "2021-06-12T01:14:14Z"
  },
  {
    "company": "Runte, Conn and Lubowitz",
    "position": "Structural Analysis Engineer",
    "status": "pending",
    "jobType": "part-time",
    "createdBy": "641924257fc4b31d10ec23d4",
    "createdAt": "2022-11-18T15:57:33Z"
  },
  {
    "company": "Schmitt-Hilll",
    "position": "Research Associate",
    "status": "interview",
    "jobType": "internship",
    "createdBy": "641924257fc4b31d10ec23d4",
    "createdAt": "2022-12-11T09:05:16Z"
  },
  {
    "company": "Dach, Larson and Klocko",
    "position": "Senior Financial Analyst",
    "status": "interview",
    "jobType": "remote",
    "createdBy": "641924257fc4b31d10ec23d4",
    "createdAt": "2022-10-09T20:04:11Z"
  },
  {
    "company": "Watsica Group",
    "position": "VP Accounting",
    "status": "interview",
    "jobType": "full-time",
    "createdBy": "641924257fc4b31d10ec23d4",
    "createdAt": "2021-05-19T06:54:15Z"
  },
  {
    "company": "Roberts-McDermott",
    "position": "Compensation Analyst",
    "status": "declined",
    "jobType": "part-time",
    "createdBy": "641924257fc4b31d10ec23d4",
    "createdAt": "2022-01-12T03:27:58Z"
  },
  {
    "company": "Luettgen, Lebsack and Satterfield",
    "position": "Clinical Specialist",
    "status": "declined",
    "jobType": "remote",
    "createdBy": "641924257fc4b31d10ec23d4",
    "createdAt": "2021-12-16T07:40:16Z"
  },
  {
    "company": "Crona, Walsh and Wolff",
    "position": "Office Assistant I",
    "status": "pending",
    "jobType": "full-time",
    "createdBy": "641924257fc4b31d10ec23d4",
    "createdAt": "2022-03-03T07:12:41Z"
  },
  {
    "company": "Kutch and Sons",
    "position": "Research Nurse",
    "status": "interview",
    "jobType": "part-time",
    "createdBy": "641924257fc4b31d10ec23d4",
    "createdAt": "2022-08-18T16:28:00Z"
  },
  {
    "company": "Stiedemann-Dibbert",
    "position": "Technical Writer",
    "status": "interview",
    "jobType": "internship",
    "createdBy": "641924257fc4b31d10ec23d4",
    "createdAt": "2022-01-06T10:20:00Z"
  },
  {
    "company": "Blanda LLC",
    "position": "Desktop Support Technician",
    "status": "declined",
    "jobType": "full-time",
    "createdBy": "641924257fc4b31d10ec23d4",
    "createdAt": "2021-11-26T20:26:56Z"
  },
  {
    "company": "Hagenes, Prohaska and Cruickshank",
    "position": "Office Assistant II",
    "status": "interview",
    "jobType": "part-time",
    "createdBy": "641924257fc4b31d10ec23d4",
    "createdAt": "2022-07-19T15:51:51Z"
  },
  {
    "company": "Kuhn Group",
    "position": "Software Engineer IV",
    "status": "interview",
    "jobType": "part-time",
    "createdBy": "641924257fc4b31d10ec23d4",
    "createdAt": "2021-08-28T08:18:38Z"
  },
  {
    "company": "Kshlerin-Keebler",
    "position": "Account Representative II",
    "status": "pending",
    "jobType": "full-time",
    "createdBy": "641924257fc4b31d10ec23d4",
    "createdAt": "2022-09-22T07:43:33Z"
  },
  {
    "company": "Adams-Koch",
    "position": "Occupational Therapist",
    "status": "pending",
    "jobType": "part-time",
    "createdBy": "641924257fc4b31d10ec23d4",
    "createdAt": "2021-08-24T22:48:37Z"
  },
  {
    "company": "Dickens, Homenick and Weber",
    "position": "Paralegal",
    "status": "interview",
    "jobType": "remote",
    "createdBy": "641924257fc4b31d10ec23d4",
    "createdAt": "2022-12-29T00:47:15Z"
  },
  {
    "company": "Ebert, Weissnat and Stanton",
    "position": "Accounting Assistant III",
    "status": "pending",
    "jobType": "full-time",
    "createdBy": "641924257fc4b31d10ec23d4",
    "createdAt": "2022-07-09T23:27:52Z"
  },
  {
    "company": "Friesen-Grant",
    "position": "General Manager",
    "status": "declined",
    "jobType": "full-time",
    "createdBy": "641924257fc4b31d10ec23d4",
    "createdAt": "2021-05-13T20:04:56Z"
  },
  {
    "company": "Bauch, Weber and Howe",
    "position": "Speech Pathologist",
    "status": "declined",
    "jobType": "internship",
    "createdBy": "641924257fc4b31d10ec23d4",
    "createdAt": "2021-08-18T19:25:52Z"
  },
  {
    "company": "Kautzer-Greenholt",
    "position": "General Manager",
    "status": "interview",
    "jobType": "full-time",
    "createdBy": "641924257fc4b31d10ec23d4",
    "createdAt": "2021-12-16T16:56:42Z"
  },
  {
    "company": "Ryan and Sons",
    "position": "Office Assistant II",
    "status": "declined",
    "jobType": "part-time",
    "createdBy": "641924257fc4b31d10ec23d4",
    "createdAt": "2022-05-02T01:47:43Z"
  },
  {
    "company": "Schuster-Konopelski",
    "position": "Account Executive",
    "status": "interview",
    "jobType": "full-time",
    "createdBy": "641924257fc4b31d10ec23d4",
    "createdAt": "2022-05-11T02:56:24Z"
  },
  {
    "company": "Hermann, Bednar and Kunde",
    "position": "Sales Representative",
    "status": "pending",
    "jobType": "internship",
    "createdBy": "641924257fc4b31d10ec23d4",
    "createdAt": "2022-07-17T12:55:14Z"
  },
  {
    "company": "Douglas-Berge",
    "position": "Computer Systems Analyst II",
    "status": "interview",
    "jobType": "part-time",
    "createdBy": "641924257fc4b31d10ec23d4",
    "createdAt": "2023-03-31T00:22:07Z"
  },
  {
    "company": "Nikolaus LLC",
    "position": "Engineer IV",
    "status": "declined",
    "jobType": "internship",
    "createdBy": "641924257fc4b31d10ec23d4",
    "createdAt": "2021-12-20T06:31:46Z"
  },
  {
    "company": "Gottlieb, Schimmel and Ziemann",
    "position": "Recruiter",
    "status": "declined",
    "jobType": "internship",
    "createdBy": "641924257fc4b31d10ec23d4",
    "createdAt": "2021-09-08T07:58:36Z"
  },
  {
    "company": "Wisozk-Larkin",
    "position": "Senior Developer",
    "status": "interview",
    "jobType": "full-time",
    "createdBy": "641924257fc4b31d10ec23d4",
    "createdAt": "2021-06-20T12:30:29Z"
  },
  {
    "company": "Lakin, Hettinger and Bergstrom",
    "position": "Administrative Officer",
    "status": "interview",
    "jobType": "remote",
    "createdBy": "641924257fc4b31d10ec23d4",
    "createdAt": "2022-10-23T19:20:18Z"
  },
  {
    "company": "Armstrong Group",
    "position": "Structural Analysis Engineer",
    "status": "pending",
    "jobType": "full-time",
    "createdBy": "641924257fc4b31d10ec23d4",
    "createdAt": "2022-06-10T18:43:01Z"
  },
  {
    "company": "Walsh, Kuphal and Cruickshank",
    "position": "Electrical Engineer",
    "status": "declined",
    "jobType": "remote",
    "createdBy": "641924257fc4b31d10ec23d4",
    "createdAt": "2022-04-13T19:13:48Z"
  },
  {
    "company": "Hammes-Smith",
    "position": "Director of Sales",
    "status": "declined",
    "jobType": "remote",
    "createdBy": "641924257fc4b31d10ec23d4",
    "createdAt": "2023-03-12T09:57:36Z"
  },
  {
    "company": "Schuppe, Bahringer and Kshlerin",
    "position": "Sales Associate",
    "status": "declined",
    "jobType": "part-time",
    "createdBy": "641924257fc4b31d10ec23d4",
    "createdAt": "2022-07-18T23:16:56Z"
  },
  {
    "company": "Heidenreich, Gutmann and Hessel",
    "position": "Engineer I",
    "status": "interview",
    "jobType": "full-time",
    "createdBy": "641924257fc4b31d10ec23d4",
    "createdAt": "2022-05-06T04:03:33Z"
  },
  {
    "company": "Steuber LLC",
    "position": "Financial Analyst",
    "status": "declined",
    "jobType": "internship",
    "createdBy": "641924257fc4b31d10ec23d4",
    "createdAt": "2021-11-15T08:58:19Z"
  },
  {
    "company": "Blanda, Hoppe and Heidenreich",
    "position": "Senior Editor",
    "status": "pending",
    "jobType": "internship",
    "createdBy": "641924257fc4b31d10ec23d4",
    "createdAt": "2021-12-07T20:53:10Z"
  },
  {
    "company": "Schmeler LLC",
    "position": "Statistician IV",
    "status": "declined",
    "jobType": "full-time",
    "createdBy": "641924257fc4b31d10ec23d4",
    "createdAt": "2022-10-16T00:59:41Z"
  },
  {
    "company": "Windler Group",
    "position": "Technical Writer",
    "status": "pending",
    "jobType": "internship",
    "createdBy": "641924257fc4b31d10ec23d4",
    "createdAt": "2022-08-18T17:03:30Z"
  },
  {
    "company": "Kris, Ebert and Rolfson",
    "position": "Recruiter",
    "status": "declined",
    "jobType": "remote",
    "createdBy": "641924257fc4b31d10ec23d4",
    "createdAt": "2021-06-16T12:55:38Z"
  },
  {
    "company": "O'Conner, Bechtelar and Goyette",
    "position": "Programmer Analyst II",
    "status": "pending",
    "jobType": "full-time",
    "createdBy": "641924257fc4b31d10ec23d4",
    "createdAt": "2022-05-14T10:24:07Z"
  },
  {
    "company": "Murphy, Pollich and Roberts",
    "position": "Assistant Manager",
    "status": "declined",
    "jobType": "internship",
    "createdBy": "641924257fc4b31d10ec23d4",
    "createdAt": "2022-03-28T23:13:24Z"
  },
  {
    "company": "Barton LLC",
    "position": "Operator",
    "status": "interview",
    "jobType": "internship",
    "createdBy": "641924257fc4b31d10ec23d4",
    "createdAt": "2021-12-16T03:53:08Z"
  },
  {
    "company": "Romaguera LLC",
    "position": "Operator",
    "status": "declined",
    "jobType": "internship",
    "createdBy": "641924257fc4b31d10ec23d4",
    "createdAt": "2021-04-21T06:16:18Z"
  },
  {
    "company": "Daniel, Bogan and Kihn",
    "position": "Chief Design Engineer",
    "status": "declined",
    "jobType": "full-time",
    "createdBy": "641924257fc4b31d10ec23d4",
    "createdAt": "2021-08-19T19:55:36Z"
  },
  {
    "company": "Daugherty-Simonis",
    "position": "Biostatistician II",
    "status": "declined",
    "jobType": "remote",
    "createdBy": "641924257fc4b31d10ec23d4",
    "createdAt": "2022-01-04T07:50:33Z"
  },
  {
    "company": "Cronin, Dooley and Wilkinson",
    "position": "Account Coordinator",
    "status": "interview",
    "jobType": "part-time",
    "createdBy": "641924257fc4b31d10ec23d4",
    "createdAt": "2022-01-11T01:38:58Z"
  },
  {
    "company": "Koss LLC",
    "position": "Structural Analysis Engineer",
    "status": "declined",
    "jobType": "remote",
    "createdBy": "641924257fc4b31d10ec23d4",
    "createdAt": "2021-06-05T12:03:35Z"
  },
  {
    "company": "Jerde Inc",
    "position": "Human Resources Manager",
    "status": "pending",
    "jobType": "part-time",
    "createdBy": "641924257fc4b31d10ec23d4",
    "createdAt": "2021-09-17T18:32:20Z"
  },
  {
    "company": "Jacobson, Pouros and Balistreri",
    "position": "VP Product Management",
    "status": "pending",
    "jobType": "internship",
    "createdBy": "641924257fc4b31d10ec23d4",
    "createdAt": "2021-09-14T07:31:16Z"
  },
  {
    "company": "Hoppe, Lemke and Dietrich",
    "position": "Senior Developer",
    "status": "interview",
    "jobType": "full-time",
    "createdBy": "641924257fc4b31d10ec23d4",
    "createdAt": "2022-11-09T20:17:56Z"
  },
  {
    "company": "Gerlach-Jones",
    "position": "Tax Accountant",
    "status": "pending",
    "jobType": "full-time",
    "createdBy": "641924257fc4b31d10ec23d4",
    "createdAt": "2022-03-26T10:59:40Z"
  },
  {
    "company": "Koss-Steuber",
    "position": "Media Manager II",
    "status": "interview",
    "jobType": "internship",
    "createdBy": "641924257fc4b31d10ec23d4",
    "createdAt": "2021-11-11T11:42:57Z"
  },
  {
    "company": "Wiegand, Lakin and Wisozk",
    "position": "Staff Accountant IV",
    "status": "declined",
    "jobType": "part-time",
    "createdBy": "641924257fc4b31d10ec23d4",
    "createdAt": "2022-11-05T15:13:22Z"
  },
  {
    "company": "Harber-Schroeder",
    "position": "Senior Editor",
    "status": "pending",
    "jobType": "full-time",
    "createdBy": "641924257fc4b31d10ec23d4",
    "createdAt": "2023-03-21T06:35:02Z"
  },
  {
    "company": "Lakin and Sons",
    "position": "Tax Accountant",
    "status": "pending",
    "jobType": "remote",
    "createdBy": "641924257fc4b31d10ec23d4",
    "createdAt": "2021-09-19T20:58:18Z"
  },
  {
    "company": "Schulist Group",
    "position": "Recruiting Manager",
    "status": "pending",
    "jobType": "internship",
    "createdBy": "641924257fc4b31d10ec23d4",
    "createdAt": "2022-05-21T16:51:23Z"
  },
  {
    "company": "Hackett, Daniel and Durgan",
    "position": "Sales Representative",
    "status": "interview",
    "jobType": "remote",
    "createdBy": "641924257fc4b31d10ec23d4",
    "createdAt": "2023-02-10T19:33:44Z"
  },
  {
    "company": "Ziemann, Ferry and Cronin",
    "position": "Nurse",
    "status": "pending",
    "jobType": "part-time",
    "createdBy": "641924257fc4b31d10ec23d4",
    "createdAt": "2022-11-04T12:15:04Z"
  },
  {
    "company": "Metz, Haley and Keebler",
    "position": "Chief Design Engineer",
    "status": "declined",
    "jobType": "full-time",
    "createdBy": "641924257fc4b31d10ec23d4",
    "createdAt": "2022-04-09T07:48:52Z"
  },
  {
    "company": "Rau-Collier",
    "position": "Business Systems Development Analyst",
    "status": "declined",
    "jobType": "remote",
    "createdBy": "641924257fc4b31d10ec23d4",
    "createdAt": "2022-11-15T12:04:43Z"
  },
  {
    "company": "Conroy-Welch",
    "position": "Geological Engineer",
    "status": "declined",
    "jobType": "remote",
    "createdBy": "641924257fc4b31d10ec23d4",
    "createdAt": "2021-11-25T10:04:29Z"
  },
  {
    "company": "Hahn, Fritsch and Homenick",
    "position": "Account Executive",
    "status": "pending",
    "jobType": "full-time",
    "createdBy": "641924257fc4b31d10ec23d4",
    "createdAt": "2022-08-06T04:36:21Z"
  },
  {
    "company": "Yundt Inc",
    "position": "Software Test Engineer IV",
    "status": "declined",
    "jobType": "internship",
    "createdBy": "641924257fc4b31d10ec23d4",
    "createdAt": "2022-08-20T12:39:16Z"
  },
  {
    "company": "McDermott Group",
    "position": "Environmental Specialist",
    "status": "declined",
    "jobType": "full-time",
    "createdBy": "641924257fc4b31d10ec23d4",
    "createdAt": "2021-05-09T15:46:06Z"
  },
  {
    "company": "Bogan and Sons",
    "position": "Database Administrator I",
    "status": "pending",
    "jobType": "remote",
    "createdBy": "641924257fc4b31d10ec23d4",
    "createdAt": "2022-03-24T20:30:55Z"
  },
  {
    "company": "Schneider Group",
    "position": "Developer II",
    "status": "interview",
    "jobType": "remote",
    "createdBy": "641924257fc4b31d10ec23d4",
    "createdAt": "2021-12-27T02:17:19Z"
  },
  {
    "company": "Cummings Inc",
    "position": "Software Engineer III",
    "status": "declined",
    "jobType": "remote",
    "createdBy": "641924257fc4b31d10ec23d4",
    "createdAt": "2022-03-05T14:15:14Z"
  },
  {
    "company": "Jakubowski, Murphy and Streich",
    "position": "Nuclear Power Engineer",
    "status": "pending",
    "jobType": "full-time",
    "createdBy": "641924257fc4b31d10ec23d4",
    "createdAt": "2023-01-01T19:40:30Z"
  },
  {
    "company": "Kuvalis, Prohaska and Hahn",
    "position": "Help Desk Operator",
    "status": "pending",
    "jobType": "part-time",
    "createdBy": "641924257fc4b31d10ec23d4",
    "createdAt": "2021-08-12T11:27:51Z"
  },
  {
    "company": "Miller LLC",
    "position": "Pharmacist",
    "status": "declined",
    "jobType": "internship",
    "createdBy": "641924257fc4b31d10ec23d4",
    "createdAt": "2021-09-10T05:36:28Z"
  },
  {
    "company": "Bruen, Monahan and Price",
    "position": "Web Designer III",
    "status": "declined",
    "jobType": "remote",
    "createdBy": "641924257fc4b31d10ec23d4",
    "createdAt": "2022-07-10T01:08:42Z"
  },
  {
    "company": "Shields Group",
    "position": "Budget/Accounting Analyst IV",
    "status": "declined",
    "jobType": "part-time",
    "createdBy": "641924257fc4b31d10ec23d4",
    "createdAt": "2022-10-11T22:04:10Z"
  },
  {
    "company": "Sawayn LLC",
    "position": "Cost Accountant",
    "status": "pending",
    "jobType": "remote",
    "createdBy": "641924257fc4b31d10ec23d4",
    "createdAt": "2021-10-28T22:59:53Z"
  }
]
